pipecat_moss/__init__.py
pipecat_moss/moss_index_processor.py
pipecat_moss/moss_retrieval_service.py
pipecat_moss-0.0.2.dist-info/licenses/LICENSE
pipecat_moss-0.0.2.dist-info/METADATA
pipecat_moss-0.0.2.dist-info/WHEEL
pipecat_moss-0.0.2.dist-info/top_level.txt
pipecat_moss-0.0.2.dist-info/RECORD
