Metadata-Version: 2.4
Name: pipecat-moss
Version: 0.0.2
Summary: Moss vector search integration for Pipecat
Requires-Python: >=3.10
License-File: LICENSE
Requires-Dist: inferedge-moss>=1.0.0b8
Requires-Dist: loguru>=0.7.0
Requires-Dist: pipecat-ai>=0.0.99
Requires-Dist: pydantic>=2.0.0
Requires-Dist: pipecat-ai[runner]>=0.0.99
Dynamic: license-file
